faint/__init__.py
faint/__main__.py
faint/branch_structure.py
faint/cli.py
faint/diff_trees.py
faint/extract_comments.py
faint/join_comments.py
faint/utils.py
faint-0.1.dist-info/entry_points.txt
faint-0.1.dist-info/LICENSE
faint-0.1.dist-info/WHEEL
faint-0.1.dist-info/METADATA
faint-0.1.dist-info/RECORD
