Metadata-Version: 2.1
Name: faint
Version: 0.1
Summary: Tool to manage your comments in code!
Author-email: Cvaniak <igna.cwaniak@gmail.com>
Requires-Python: >=3.7
Classifier: License :: OSI Approved :: MIT License
Requires-Dist: typer==0.12.3
Requires-Dist: tree-sitter-python==0.21.0
Requires-Dist: tree-sitter==0.22.3
Requires-Dist: GitPython==3.1.43
